google/api/annotations_pb2.py
google/api/annotations_pb2_grpc.py
google/api/client_pb2.py
google/api/client_pb2_grpc.py
google/api/field_behavior_pb2.py
google/api/field_behavior_pb2_grpc.py
google/api/http_pb2.py
google/api/http_pb2_grpc.py
google/api/launch_stage_pb2.py
google/api/launch_stage_pb2_grpc.py
identityservice/__init__.py
identityservice/__main__.py
identityservice/cli.py
identityservice/client.py
identityservice/constant.py
identityservice/sdk.py
identityservice/auth/__init__.py
identityservice/auth/common.py
identityservice/auth/httpx.py
identityservice/auth/starlette.py
identityservice/badge/a2a.py
identityservice/badge/mcp.py
identityservice/commands/badge.py
openapiv3/OpenAPIv3_pb2.py
openapiv3/OpenAPIv3_pb2_grpc.py
openapiv3/annotations_pb2.py
openapiv3/annotations_pb2_grpc.py
outshift/identity/service/shared/v1alpha1/pagination_pb2.py
outshift/identity/service/shared/v1alpha1/pagination_pb2_grpc.py
outshift/identity/service/v1alpha1/app_pb2.py
outshift/identity/service/v1alpha1/app_pb2_grpc.py
outshift/identity/service/v1alpha1/app_service_pb2.py
outshift/identity/service/v1alpha1/app_service_pb2_grpc.py
outshift/identity/service/v1alpha1/auth_pb2.py
outshift/identity/service/v1alpha1/auth_pb2_grpc.py
outshift/identity/service/v1alpha1/auth_service_pb2.py
outshift/identity/service/v1alpha1/auth_service_pb2_grpc.py
outshift/identity/service/v1alpha1/badge_pb2.py
outshift/identity/service/v1alpha1/badge_pb2_grpc.py
outshift/identity/service/v1alpha1/badge_service_pb2.py
outshift/identity/service/v1alpha1/badge_service_pb2_grpc.py
outshift/identity/service/v1alpha1/device_pb2.py
outshift/identity/service/v1alpha1/device_pb2_grpc.py
outshift/identity/service/v1alpha1/device_service_pb2.py
outshift/identity/service/v1alpha1/device_service_pb2_grpc.py
outshift/identity/service/v1alpha1/openapi_pb2.py
outshift/identity/service/v1alpha1/openapi_pb2_grpc.py
outshift/identity/service/v1alpha1/policy_pb2.py
identity_service_sdk-0.0.3.dist-info/METADATA
identity_service_sdk-0.0.3.dist-info/WHEEL
identity_service_sdk-0.0.3.dist-info/entry_points.txt
identity_service_sdk-0.0.3.dist-info/top_level.txt
identity_service_sdk-0.0.3.dist-info/RECORD
